PyOGC/__init__.py
PyOGC/collections.py
PyOGC/conformace.py
PyOGC/landing.py
tests/__init__.py
tests/test_tiling.py
PyOGC-0.0.3.dist-info/LICENSE
PyOGC-0.0.3.dist-info/METADATA
PyOGC-0.0.3.dist-info/WHEEL
PyOGC-0.0.3.dist-info/top_level.txt
PyOGC-0.0.3.dist-info/RECORD
