Metadata-Version: 2.1
Name: PyOGC
Version: 0.0.3
Summary: Unified OGC Api Python Client
Author: Ryanwalker277 (Anvansh)
Author-email: <anvansh30mar@gmail.com>
Keywords: python,video,OGC,API,client,unified,pyogc,pyogcclient
Classifier: Development Status :: 1 - Planning
Classifier: Intended Audience :: Developers
Classifier: Programming Language :: Python :: 3
Classifier: Operating System :: Unix
Classifier: Operating System :: MacOS :: MacOS X
Classifier: Operating System :: Microsoft :: Windows
License-File: LICENSE
Requires-Dist: requests
Requires-Dist: pytest
